dj_rql/__init__.py
dj_rql/_dataclasses.py
dj_rql/constants.py
dj_rql/drf/__init__.py
dj_rql/drf/_utils.py
dj_rql/drf/backend.py
dj_rql/drf/compat.py
dj_rql/drf/paginations.py
dj_rql/drf/serializers.py
dj_rql/fields.py
dj_rql/filter_cls.py
dj_rql/management/__init__.py
dj_rql/management/commands/__init__.py
dj_rql/management/commands/generate_rql_class.py
dj_rql/openapi.py
dj_rql/qs.py
dj_rql/transformer.py
dj_rql/utils.py
django_rql-4.3.0.dist-info/LICENSE
django_rql-4.3.0.dist-info/METADATA
django_rql-4.3.0.dist-info/WHEEL
django_rql-4.3.0.dist-info/RECORD
