Metadata-Version: 2.1
Name: django-rql
Version: 4.3.0
Summary: Django RQL Filtering
Home-page: https://connect.cloudblue.com/community/api/rql/
License: Apache-2.0
Keywords: django,rql,filter,rest,api
Author: Ingram Micro
Requires-Python: >=3.7,<4
Classifier: Development Status :: 5 - Production/Stable
Classifier: Framework :: Django :: 3.2
Classifier: Framework :: Django :: 4.0
Classifier: Framework :: Django :: 4.1
Classifier: Framework :: Django :: 4.2
Classifier: Intended Audience :: Developers
Classifier: License :: OSI Approved :: Apache Software License
Classifier: Operating System :: Unix
Classifier: Programming Language :: Python :: 3
Classifier: Programming Language :: Python :: 3.7
Classifier: Programming Language :: Python :: 3.8
Classifier: Programming Language :: Python :: 3.9
Classifier: Programming Language :: Python :: 3.10
Classifier: Programming Language :: Python :: 3.11
Classifier: Programming Language :: Python :: 3.10
Classifier: Programming Language :: Python :: 3.11
Classifier: Programming Language :: Python :: 3.7
Classifier: Programming Language :: Python :: 3.8
Classifier: Programming Language :: Python :: 3.9
Classifier: Topic :: Text Processing :: Filters
Requires-Dist: django (>=3.2)
Requires-Dist: lib-rql (>=1.1.5,<2.0.0)
Project-URL: Repository, https://github.com/cloudblue/django-rql
